stockit/SSRR.py
stockit/__init__.py
stockit/dataGraber.py
stockit/regressorEdgeCases.py
stockit/stockit_class.py
stockit/stockit_class_test.py
stockit-1.0.9.1.dist-info/LICENSE.txt
stockit-1.0.9.1.dist-info/METADATA
stockit-1.0.9.1.dist-info/WHEEL
stockit-1.0.9.1.dist-info/top_level.txt
stockit-1.0.9.1.dist-info/RECORD
