Metadata-Version: 2.1
Name: stockit
Version: 1.0.9.1
Summary: Python module containing a bundle of algorithms for financial analysis and future stock price estimations.
Home-page: https://github.com/BenCaunt8300/stockit
Author: Ben Caunt
Author-email: bdcaunt@gmail.com
License: Apache 2.0
Download-URL: https://github.com/BenCaunt8300/stockit/archive/v1.0.9.1.tar.gz
Platform: UNKNOWN
Classifier: Development Status :: 3 - Alpha
Classifier: Intended Audience :: Developers
Classifier: Topic :: Software Development :: Build Tools
Classifier: License :: OSI Approved :: Apache Software License
Classifier: Programming Language :: Python :: 3.6
Classifier: Programming Language :: Python :: 3.7
Classifier: Programming Language :: Python :: 3.8
Requires-Dist: pandas
Requires-Dist: numpy
Requires-Dist: matplotlib
Requires-Dist: tqdm
Requires-Dist: sklearn
Requires-Dist: pandas-datareader
